magento_client/__init__.py
magento_client/cli.py
magento_client/magento_client.py
magento_client/rest_client.py
magento_client-0.1.1.dist-info/AUTHORS.rst
magento_client-0.1.1.dist-info/LICENSE
magento_client-0.1.1.dist-info/METADATA
magento_client-0.1.1.dist-info/WHEEL
magento_client-0.1.1.dist-info/entry_points.txt
magento_client-0.1.1.dist-info/top_level.txt
magento_client-0.1.1.dist-info/RECORD
