Metadata-Version: 2.1
Name: magento-client
Version: 0.1.1
Summary: a client to comunicate with magento API
Home-page: https://github.com/sveinok/magento_client
Author: Svein Økland
Author-email: svein@tinyelephant.no
License: MIT license
Keywords: magento_client
Platform: UNKNOWN
Classifier: Development Status :: 2 - Pre-Alpha
Classifier: Intended Audience :: Developers
Classifier: License :: OSI Approved :: MIT License
Classifier: Natural Language :: English
Classifier: Programming Language :: Python :: 3
Classifier: Programming Language :: Python :: 3.5
Classifier: Programming Language :: Python :: 3.6
Classifier: Programming Language :: Python :: 3.7
Classifier: Programming Language :: Python :: 3.8
Requires-Python: >=3.5
Requires-Dist: Click (>=7.0)
